ryland/__init__.py
ryland/core.py
ryland/helpers.py
ryland/py.typed
ryland/tubes.py
ryland-0.16.0.dist-info/WHEEL
ryland-0.16.0.dist-info/METADATA
ryland-0.16.0.dist-info/RECORD
