Metadata-Version: 2.4
Name: ryland
Version: 0.16.0
Summary: A simple static site generation library
Author: James Tauber
Author-email: James Tauber <jtauber@jtauber.com>
License-Expression: MIT
Requires-Dist: jinja2>=3.1.6
Requires-Dist: markdown>=3.9
Requires-Dist: pyyaml>=6.0.2
Requires-Dist: pillow>=12.0.0
Requires-Python: >=3.12
Project-URL: github, https://github.com/jtauber/ryland
